explicit/__init__.py
explicit/waiter.py
explicit-0.1.3.dist-info/DESCRIPTION.rst
explicit-0.1.3.dist-info/METADATA
explicit-0.1.3.dist-info/RECORD
explicit-0.1.3.dist-info/WHEEL
explicit-0.1.3.dist-info/metadata.json
explicit-0.1.3.dist-info/pbr.json
explicit-0.1.3.dist-info/top_level.txt
